toc2audio.py
toc2audio-1.1.1.dist-info/entry_points.txt
toc2audio-1.1.1.dist-info/LICENSE.txt
toc2audio-1.1.1.dist-info/WHEEL
toc2audio-1.1.1.dist-info/METADATA
toc2audio-1.1.1.dist-info/RECORD
