Metadata-Version: 2.1
Name: toc2audio
Version: 1.1.1
Summary: Add Table of Contents and chapters to audio files
Author-email: Jesús Cea Avión <jcea@jcea.es>
Requires-Python: >=3.7
Classifier: Development Status :: 5 - Production/Stable
Classifier: License :: OSI Approved :: GNU Affero General Public License v3
Classifier: Topic :: Multimedia :: Sound/Audio :: Editors
Requires-Dist: mutagen
Requires-Dist: markdown
Project-URL: Changelog, https://docs.jcea.es/toc2audio/changelog.html
Project-URL: Documentation, https://docs.jcea.es/toc2audio/
Project-URL: Homepage, https://docs.jcea.es/toc2audio/
Project-URL: Repository, https://hg.jcea.es/toc2audio/
Project-URL: ToDo, https://docs.jcea.es/toc2audio/todo.html
